{"stats":{"minecraft:picked_up":{"minecraft:mutton":2,"minecraft:white_wool":1},"minecraft:killed":{"minecraft:sheep":1},"minecraft:custom":{"minecraft:jump":14,"minecraft:time_since_rest":8786,"minecraft:damage_dealt":20,"minecraft:crouch_one_cm":920,"minecraft:sprint_one_cm":2107,"minecraft:leave_game":2,"minecraft:play_time":8786,"minecraft:time_since_death":8786,"minecraft:walk_one_cm":9813,"minecraft:sneak_time":454,"minecraft:total_world_time":8786,"minecraft:mob_kills":1,"minecraft:fall_one_cm":16648,"minecraft:fly_one_cm":12029,"minecraft:aviate_one_cm":189580}},"DataVersion":2730}